{
    "configurations": [
        {
            "browse": {
                "databaseFilename": "${default}",
                "limitSymbolsToIncludedHeaders": false
            },
            "includePath": [
                "/opt/ros/humble/include/**",
                "/home/ahmad/InmindFinal/src/robot_driver/include/**",
                "/usr/include/**",
                "${workspaceFolder}"
            ],
            "name": "ROS",
            "intelliSenseMode": "gcc-x64",
            "compilerPath": "/usr/bin/g++",
            "cStandard": "gnu11",
            "cppStandard": "c++14"
        }
    ],
    "version": 4
}